plugfn/__init__.py
plugfn/types.py
plugfn/adapters/__init__.py
plugfn/adapters/fastapi.py
plugfn/adapters/flask.py
plugfn/auth/__init__.py
plugfn/auth/oauth_flow.py
plugfn/auth/token_store.py
plugfn/core/__init__.py
plugfn/core/action_executor.py
plugfn/core/connection_manager.py
plugfn/core/plug_fn.py
plugfn/core/provider_registry.py
plugfn/core/workflow_engine.py
plugfn/http/__init__.py
plugfn/http/http_client.py
plugfn/providers/__init__.py
plugfn/providers/github.py
plugfn/providers/slack.py
plugfn/storage/__init__.py
plugfn/storage/connection_storage.py
plugfn/storage/token_storage.py
plugfn/storage/workflow_storage.py
plugfn/utils/__init__.py
plugfn/utils/logger.py
plugfn/webhooks/__init__.py
plugfn/webhooks/webhook_handler.py
plugfn-0.0.1.dist-info/METADATA
plugfn-0.0.1.dist-info/WHEEL
plugfn-0.0.1.dist-info/RECORD
